Metadata-Version: 1.0
Name: deep-probability
Version: 1.0
Summary: Gaussian and Binomial distributions
Home-page: UNKNOWN
Author: Deep Rodge
Author-email: deeprodge14@gmail.com
License: UNKNOWN
Platform: UNKNOWN
